LICENSE
README.md
setup.py
google_business_listing_scraper/__init__.py
google_business_listing_scraper.egg-info/PKG-INFO
google_business_listing_scraper.egg-info/SOURCES.txt
google_business_listing_scraper.egg-info/dependency_links.txt
google_business_listing_scraper.egg-info/requires.txt
google_business_listing_scraper.egg-info/top_level.txt