Metadata-Version: 2.1
Name: google-business-listing-scraper
Version: 1.0.1
Summary: A python library to scrape google business listing
Home-page: UNKNOWN
Author: DataKund
Author-email: datakund@gmail.com
License: Apache License 2.0
Keywords: google python bot_studio automation search businesslisting scraper title description link
Platform: UNKNOWN
License-File: LICENSE
